{"importBase":"import","nativeBase":"native","name":"resources","deps":[],"uuids":["02eafd93d","03173da80","03f7d5663","03fc4da34","05hfMzGEtNA6GbnvhOBr9P","06f1f906a","06fb83abd","08667ce05","08aaf39a9","096f0f6d7","09nNY24rdEoYVLfHk4g/3x","26ZHWT0oxCjr1Av2K4A+Yw","09nNY24rdEoYVLfHk4g/3x@6c48a","09nNY24rdEoYVLfHk4g/3x@f9941","0aHD9U5YFG9Kzal8ELWbdd","0aHD9U5YFG9Kzal8ELWbdd@6c48a","0aHD9U5YFG9Kzal8ELWbdd@f9941","0c4f9b34a","0e6db5cc0","0f3bb00fb","0f49146a3","20g1ukYUVPvKWKBRznAKo+","45UJfkLEtDep6qcZ006HpC","20g1ukYUVPvKWKBRznAKo+@6c48a","20g1ukYUVPvKWKBRznAKo+@f9941","24pwTaKGdEbY0aXpIMdeCd","24pwTaKGdEbY0aXpIMdeCd@6c48a","24pwTaKGdEbY0aXpIMdeCd@f9941","24xBnqY6hOoanQf8RpSJu8","24xBnqY6hOoanQf8RpSJu8@6c48a","24xBnqY6hOoanQf8RpSJu8@f9941","33GrEaiUlB7asW86uJvVgf","35t1IycVNAVJ04W/RswjmD","43d++hrUlESaAMWq9HymqO","45jUi0SoJL4J3D1MZ4j0H+","33GrEaiUlB7asW86uJvVgf@6c48a","33GrEaiUlB7asW86uJvVgf@f9941","33J2cpdSZFc7ld5f8c5rRP","33J2cpdSZFc7ld5f8c5rRP@6c48a","33J2cpdSZFc7ld5f8c5rRP@f9941","41REkAj65InrHUDt+FalVH","41REkAj65InrHUDt+FalVH@6c48a","41REkAj65InrHUDt+FalVH@f9941","41VdElYghKkr9QWDuhi8By","41VdElYghKkr9QWDuhi8By@6c48a","41VdElYghKkr9QWDuhi8By@f9941","4aqlN8V45GoI0uWS3FJKye","4aqlN8V45GoI0uWS3FJKye@6c48a","4aqlN8V45GoI0uWS3FJKye@f9941","52jGqaDFZFAruNCZ4bWPKZ","52jGqaDFZFAruNCZ4bWPKZ@6c48a","52jGqaDFZFAruNCZ4bWPKZ@f9941","54TknWPwVPqJqeCR+Y/Czo","5fJJAfexRLuab5Hsb4/KCK","54TknWPwVPqJqeCR+Y/Czo@f9941","5fOQmXuNdLyKFXsko3ybrL","60kxt4Y2BD2Zk0zfXpsNEx","66ea7ZnFtLZJy18MDfO4N7","93sxkjypFFUajDPRFpzvQ7","famjg/znxPg6iP8SZ6DqeL","60kxt4Y2BD2Zk0zfXpsNEx@6c48a","60kxt4Y2BD2Zk0zfXpsNEx@f9941","6euZOXe9tKoYqYfm0HcK39","d7UOYhzadE0KHN716pfEdA","e5XJJPEwhNg6yB8o6NWt+I","54TknWPwVPqJqeCR+Y/Czo@6c48a","6euZOXe9tKoYqYfm0HcK39@6c48a","6euZOXe9tKoYqYfm0HcK39@f9941","6e8u0GjtBK/pl69esezcA1","72sHObV7FP0rC8HXk78ae8","b11RDnKo5MG4ZzxAo9ncOJ","72sHObV7FP0rC8HXk78ae8@6c48a","72sHObV7FP0rC8HXk78ae8@f9941","80Sr08Ia9Ar4DM0O0X2/sK","80Sr08Ia9Ar4DM0O0X2/sK@6c48a","80Sr08Ia9Ar4DM0O0X2/sK@f9941","81uoyHqGRF+5MEDTXETTDo","81uoyHqGRF+5MEDTXETTDo@6c48a","81uoyHqGRF+5MEDTXETTDo@f9941","85c16qiQhKubf4jdujqZgp","dfx0Tp131F+p0jX/vW3BhE","85c16qiQhKubf4jdujqZgp@6c48a","85c16qiQhKubf4jdujqZgp@f9941","868l1cneVFT6X57hZgPmcB","95EkngnxZFbYuFpsqVTaFr","95EkngnxZFbYuFpsqVTaFr@6c48a","95EkngnxZFbYuFpsqVTaFr@f9941","95toCW5KBP+7pgmdsnOh92","95toCW5KBP+7pgmdsnOh92@6c48a","95toCW5KBP+7pgmdsnOh92@f9941","a6z2jNZfpPjpBj1tC1Dl9C","b7ARGCcWpOloxGPSfig1zm","b7ARGCcWpOloxGPSfig1zm@6c48a","b7ARGCcWpOloxGPSfig1zm@f9941","bcU3NMn+VJXozK/pH7J3RQ","f04K1NRjtAEZRs5vGUxjWE","bcU3NMn+VJXozK/pH7J3RQ@6c48a","bcU3NMn+VJXozK/pH7J3RQ@f9941","d21WnfWZxIj4Ii0PGArm/H","e08aquBedNRokvR+pMAWxT","e1e0UmV6JI06zJzwnzCqE4","eeStX/l65C/5bCu2gWxys4","eeStX/l65C/5bCu2gWxys4@6c48a","eeStX/l65C/5bCu2gWxys4@f9941","f8NbLX4uZAPreT+LKDCKEX","fbzth0D4lGL6XRe0RKP5zg","f8NbLX4uZAPreT+LKDCKEX@6c48a","f8NbLX4uZAPreT+LKDCKEX@f9941"],"paths":{"4":["prefabs/giftboxs/randomBox",1],"11":["prefabs/awards/weaponX1",1],"22":["prefabs/particles/explosion",1],"32":["prefabs/awards/weaponX4",1],"33":["prefabs/enemy",1],"34":["prefabs/particles/bulletHit",1],"53":["prefabs/awards/weaponX2",1],"55":["prefabs/particles/pushfire",2],"57":["prefabs/bullets/bullet",1],"58":["prefabs/gameLevels/Lv2",1],"59":["prefabs/gameLevels/Lv1",1],"63":["prefabs/ui/dialog",1],"64":["prefabs/gameLevels/Lv3",1],"68":["prefabs/particles/bom",1],"70":["fonts/AaJiJiaHei-2",0],"80":["prefabs/awards/weaponX5",1],"95":["prefabs/awards/weaponX3",1],"99":["prefabs/ui/toast",1],"105":["prefabs/bullets/enemyBullet",1]},"scenes":{},"packs":{"02eafd93d":["32","48"],"03173da80":["61","95"],"03f7d5663":["11","39","67","75"],"03fc4da34":["107","59"],"06f1f906a":["4","13","27","30","22","72","83","70","98","100","103"],"06fb83abd":["33","78","89","105"],"08667ce05":["16","36","53"],"08aaf39a9":["42","64"],"096f0f6d7":["45","51","80"],"0c4f9b34a":["24","54","82","86","93","63"],"0e6db5cc0":["15","47","66","26","29","71","77","88","12","35","50","65","74","44","23","60","81","85","38","41","92","96","102","106"],"0f3bb00fb":["34","57"],"0f49146a3":["58","90","97"]},"versions":{"import":[],"native":[]},"redirect":[],"debug":false,"extensionMap":{},"hasPreloadScript":true,"dependencyRelationships":{"4":["100","72","70","27","103","22","13"],"11":["75","39","67"],"12":["10"],"13":["12"],"15":["14"],"16":["15"],"22":["83","30","98"],"23":["21"],"24":["23"],"26":["25"],"27":["26"],"29":["28"],"30":["29"],"32":["75","48","67"],"33":["89","22","105"],"34":["83","30"],"35":["31"],"36":["35"],"38":["37"],"39":["38"],"41":["40"],"42":["41"],"44":["43"],"45":["44"],"47":["46"],"48":["47"],"50":["49"],"51":["50"],"53":["75","36","16"],"54":["65"],"55":["30"],"57":["30","34"],"58":["97","90"],"59":["107","90"],"60":["56"],"61":["60"],"63":["70","103","82","24","54","86","93"],"64":["42","90"],"65":["52"],"66":["62"],"67":["66"],"68":["100","72"],"71":["69"],"72":["71"],"74":["73"],"75":["74"],"77":["76"],"78":["77"],"80":["75","45","51"],"81":["79"],"82":["81"],"83":["30"],"85":["84"],"86":["85"],"88":["87"],"89":["88"],"92":["91"],"93":["92"],"95":["75","61","72"],"96":["94"],"97":["96"],"99":["70"],"100":["30"],"102":["101"],"103":["102"],"105":["78"],"106":["104"],"107":["106"]},"types":["cc.TTFFont","cc.Prefab","cc.ParticleAsset"]}